{
  "pmcid": "1216327",
  "raw_text": "```json\n[\n  {\n    \"pmcid\": \"PMC1199607\",\n    \"outcome\": \"The mean body weight gain\",\n    \"intervention\": \"White Grape Juice (WGJ)\",\n    \"comparator\": \"colored and flavored water (WA)\",\n    \"outcome_type\": \"continuous\",\n    \"intervention_events\": null,\n    \"intervention_group_size\": 30,\n    \"comparator_events\": null,\n    \"comparator_group_size\": 30,\n    \"intervention_mean\": 50.6,\n    \"intervention_standard_deviation\": null,\n    \"comparator_mean\": -7.0,\n    \"comparator_standard_deviation\": null,\n    \"comparator_standard_deviation\": null,\n    \"notes\": \"Mean body weight gain reported in grams in Results: 'there was a mean weight gain of 18.3 gm in the AJ fed patients and of 50.6 gm in those given WGJ, whereas there was a mean loss of body weight (- 7.0 gm) among the WA group patients (p = 0.08)'. No SDs reported for weight change by group.\",\n    \"pmcid\": \"PMC1199607\"\n  },\n  {\n    \"pmcid\": \"PMC1199607\",\n    \"outcome\": \"The duration of the illness\",\n    \"intervention\": \"White Grape Juice (WGJ)\",\n    \"comparator\": \"colored and flavored water (WA)\",\n    \"outcome_type\": \"continuous\",\n    \"intervention_events\": null,\n    \"intervention_group_size\": 30,\n    \"comparator_events\": null,\n    \"comparator_group_size\": 30,\n    \"intervention_mean\": 47.5,\n    \"intervention_standard_deviation\": 38.9,\n    \"comparator_mean\": 26.5,\n    \"comparator_standard_deviation\": 27.4,\n    \"notes\": \"Duration of diarrhea after randomization, in hours, from Table 5: 'The mean +/- SD duration in hours was 49.4 \u00b1 32.6, 47.5 \u00b1 38.9 and 26.5 \u00b1 27.4 in patients fed AJ, WGJ and WA respectively.'\",\n    \"pmcid\": \"PMC1199607\"\n  },\n  {\n    \"pmcid\": \"PMC1199607\",\n    \"outcome\": \"The fecal losses\",\n    \"intervention\": \"White Grape Juice (WGJ)\",\n    \"comparator\": \"colored and flavored water (WA)\",\n    \"outcome_type\": \"continuous\",\n    \"intervention_events\": null,\n    \"intervention_group_size\": 30,\n    \"comparator_events\": null,\n    \"comparator_group_size\": 30,\n    \"intervention_mean\": 3.59,\n    \"intervention_standard_deviation\": 2.35,\n    \"comparator_mean\": 2.19,\n    \"comparator_standard_deviation\": 1.63,\n    \"notes\": \"Total fecal losses over the study period in g/kg/h from Table 6: 'The mean \u00b1 SD fecal excretion in g/kg/h was 3.94 \u00b1 2.35, 3.59 \u00b1 2.35, and 2.19 \u00b1 1.63 in AJ, WGJ and WA respectively.' First-day losses are also reported but the overall total is extracted here.\",\n    \"pmcid\": \"PMC1199607\"\n  }\n]\n```",
  "extraction": [
    {
      "pmcid": "PMC1199607",
      "outcome": "The mean body weight gain",
      "intervention": "White Grape Juice (WGJ)",
      "comparator": "colored and flavored water (WA)",
      "outcome_type": "continuous",
      "intervention_events": null,
      "intervention_group_size": 30,
      "comparator_events": null,
      "comparator_group_size": 30,
      "intervention_mean": 50.6,
      "intervention_standard_deviation": null,
      "comparator_mean": -7.0,
      "comparator_standard_deviation": null,
      "notes": "Mean body weight gain reported in grams in Results: 'there was a mean weight gain of 18.3 gm in the AJ fed patients and of 50.6 gm in those given WGJ, whereas there was a mean loss of body weight (- 7.0 gm) among the WA group patients (p = 0.08)'. No SDs reported for weight change by group."
    },
    {
      "pmcid": "PMC1199607",
      "outcome": "The duration of the illness",
      "intervention": "White Grape Juice (WGJ)",
      "comparator": "colored and flavored water (WA)",
      "outcome_type": "continuous",
      "intervention_events": null,
      "intervention_group_size": 30,
      "comparator_events": null,
      "comparator_group_size": 30,
      "intervention_mean": 47.5,
      "intervention_standard_deviation": 38.9,
      "comparator_mean": 26.5,
      "comparator_standard_deviation": 27.4,
      "notes": "Duration of diarrhea after randomization, in hours, from Table 5: 'The mean +/- SD duration in hours was 49.4 \u00b1 32.6, 47.5 \u00b1 38.9 and 26.5 \u00b1 27.4 in patients fed AJ, WGJ and WA respectively.'"
    },
    {
      "pmcid": "PMC1199607",
      "outcome": "The fecal losses",
      "intervention": "White Grape Juice (WGJ)",
      "comparator": "colored and flavored water (WA)",
      "outcome_type": "continuous",
      "intervention_events": null,
      "intervention_group_size": 30,
      "comparator_events": null,
      "comparator_group_size": 30,
      "intervention_mean": 3.59,
      "intervention_standard_deviation": 2.35,
      "comparator_mean": 2.19,
      "comparator_standard_deviation": 1.63,
      "notes": "Total fecal losses over the study period in g/kg/h from Table 6: 'The mean \u00b1 SD fecal excretion in g/kg/h was 3.94 \u00b1 2.35, 3.59 \u00b1 2.35, and 2.19 \u00b1 1.63 in AJ, WGJ and WA respectively.' First-day losses are also reported but the overall total is extracted here."
    }
  ],
  "usage": {
    "input": 0,
    "output": 0
  },
  "model": "gpt",
  "strategy": "zero-shot",
  "temperature": 0.0
}