{
  "pmcid": "3276927",
  "raw_text": "```json\n[\n  {\n    \"pmcid\": null,\n    \"outcome\": \"relieving factors in reversible inguinal hernia\",\n    \"intervention\": \"post-Yoga\",\n    \"comparator\": \"pre-Yoga\",\n    \"outcome_type\": \"continuous\",\n    \"intervention_events\": null,\n    \"intervention_group_size\": 19,\n    \"comparator_events\": null,\n    \"comparator_group_size\": 19,\n    \"intervention_mean\": null,\n    \"intervention_standard_deviation\": null,\n    \"comparator_mean\": null,\n    \"comparator_standard_deviation\": null,\n    \"notes\": \"Only medians and ranges reported. Before: median 2 (range 1\u20133); After: median 3 (all 3). Wilcoxon signed-rank z=3.391, P<0.001.\",\n    \"pmcid\": null\n  },\n  {\n    \"pmcid\": null,\n    \"outcome\": \"effective in the treatment of reversible inguinal hernia\",\n    \"intervention\": \"post-Yoga\",\n    \"comparator\": \"pre-Yoga\",\n    \"outcome_type\": null,\n    \"intervention_events\": null,\n    \"intervention_group_size\": 19,\n    \"comparator_events\": null,\n    \"comparator_group_size\": 19,\n    \"intervention_mean\": null,\n    \"intervention_standard_deviation\": null,\n    \"comparator_mean\": null,\n    \"comparator_standard_deviation\": null,\n    \"notes\": \"Overall effectiveness is concluded qualitatively from multiple symptom outcomes; no single numeric outcome directly labeled as 'effective in the treatment' is reported.\",\n    \"pmcid\": null\n  },\n  {\n    \"pmcid\": null,\n    \"outcome\": \"frequency of occurrence in reversible inguinal hernia\",\n    \"intervention\": \"post-Yoga\",\n    \"comparator\": \"pre-Yoga\",\n    \"outcome_type\": \"continuous\",\n    \"intervention_events\": null,\n    \"intervention_group_size\": 19,\n    \"comparator_events\": null,\n    \"comparator_group_size\": 19,\n    \"intervention_mean\": null,\n    \"intervention_standard_deviation\": null,\n    \"comparator_mean\": null,\n    \"comparator_standard_deviation\": null,\n    \"notes\": \"Frequency measured as number of times hernia occurred in last two weeks. Before: median 12 (range 9\u201314, Q1=10, Q3=14, QD=2); After: median 2 (range 0\u20136, Q1=1, Q3=3, QD=1). Wilcoxon signed-rank z=\u22123.835, P<0.001.\",\n    \"pmcid\": null\n  },\n  {\n    \"pmcid\": null,\n    \"outcome\": \"symptoms of hernia such as heaviness, fullness and pain\",\n    \"intervention\": \"post-Yoga\",\n    \"comparator\": \"pre-Yoga\",\n    \"outcome_type\": \"continuous\",\n    \"intervention_events\": null,\n    \"intervention_group_size\": 19,\n    \"comparator_events\": null,\n    \"comparator_group_size\": 19,\n    \"intervention_mean\": null,\n    \"intervention_standard_deviation\": null,\n    \"comparator_mean\": null,\n    \"comparator_standard_deviation\": null,\n    \"notes\": \"Article states yoga practices are useful in reducing symptoms such as heaviness, fullness and pain, but only pain intensity is quantified. Pain before: median 6 (range 3\u20138, Q1=5, Q3=7, QD=1); after: median 1 (range 0\u20133, Q1=0, Q3=2, QD=1). Wilcoxon signed-rank z=\u22123.864, P<0.001. No separate quantitative data for heaviness or fullness.\",\n    \"pmcid\": null\n  },\n  {\n    \"pmcid\": null,\n    \"outcome\": \"pain in reversible inguinal hernia\",\n    \"intervention\": \"post-Yoga\",\n    \"comparator\": \"pre-Yoga\",\n    \"outcome_type\": \"continuous\",\n    \"intervention_events\": null,\n    \"intervention_group_size\": 19,\n    \"comparator_events\": null,\n    \"comparator_group_size\": 19,\n    \"intervention_mean\": null,\n    \"intervention_standard_deviation\": null,\n    \"comparator_mean\": null,\n    \"comparator_standard_deviation\": null,\n    \"notes\": \"Pain measured on 0\u201310 numeric rating scale. Before: median 6 (range 3\u20138, Q1=5, Q3=7, QD=1); After: median 1 (range 0\u20133, Q1=0, Q3=2, QD=1). Wilcoxon signed-rank z=\u22123.864, P<0.001. Means and SDs not reported.\",\n    \"pmcid\": null\n  },\n  {\n    \"pmcid\": null,\n    \"outcome\": \"aggravating factors in reversible inguinal hernia\",\n    \"intervention\": \"post-Yoga\",\n    \"comparator\": \"pre-Yoga\",\n    \"outcome_type\": \"continuous\",\n    \"intervention_events\": null,\n    \"intervention_group_size\": 19,\n    \"comparator_events\": null,\n    \"comparator_group_size\": 19,\n    \"intervention_mean\": null,\n    \"intervention_standard_deviation\": null,\n    \"comparator_mean\": null,\n    \"comparator_standard_deviation\": null,\n    \"notes\": \"Aggravating factors scored as count of present activities (0\u20135) among exercise/walking, bowel movement, bladder activity, lifting, coughing/sneezing. Before: median 4 (range 3\u20135, QD=0.5); After: median 1 (range 0\u20132, QD=0). Wilcoxon signed-rank z=\u22123.875, P<0.001.\",\n    \"pmcid\": null\n  }\n]\n```",
  "extraction": [
    {
      "pmcid": null,
      "outcome": "relieving factors in reversible inguinal hernia",
      "intervention": "post-Yoga",
      "comparator": "pre-Yoga",
      "outcome_type": "continuous",
      "intervention_events": null,
      "intervention_group_size": 19,
      "comparator_events": null,
      "comparator_group_size": 19,
      "intervention_mean": null,
      "intervention_standard_deviation": null,
      "comparator_mean": null,
      "comparator_standard_deviation": null,
      "notes": "Only medians and ranges reported. Before: median 2 (range 1\u20133); After: median 3 (all 3). Wilcoxon signed-rank z=3.391, P<0.001."
    },
    {
      "pmcid": null,
      "outcome": "effective in the treatment of reversible inguinal hernia",
      "intervention": "post-Yoga",
      "comparator": "pre-Yoga",
      "outcome_type": null,
      "intervention_events": null,
      "intervention_group_size": 19,
      "comparator_events": null,
      "comparator_group_size": 19,
      "intervention_mean": null,
      "intervention_standard_deviation": null,
      "comparator_mean": null,
      "comparator_standard_deviation": null,
      "notes": "Overall effectiveness is concluded qualitatively from multiple symptom outcomes; no single numeric outcome directly labeled as 'effective in the treatment' is reported."
    },
    {
      "pmcid": null,
      "outcome": "frequency of occurrence in reversible inguinal hernia",
      "intervention": "post-Yoga",
      "comparator": "pre-Yoga",
      "outcome_type": "continuous",
      "intervention_events": null,
      "intervention_group_size": 19,
      "comparator_events": null,
      "comparator_group_size": 19,
      "intervention_mean": null,
      "intervention_standard_deviation": null,
      "comparator_mean": null,
      "comparator_standard_deviation": null,
      "notes": "Frequency measured as number of times hernia occurred in last two weeks. Before: median 12 (range 9\u201314, Q1=10, Q3=14, QD=2); After: median 2 (range 0\u20136, Q1=1, Q3=3, QD=1). Wilcoxon signed-rank z=\u22123.835, P<0.001."
    },
    {
      "pmcid": null,
      "outcome": "symptoms of hernia such as heaviness, fullness and pain",
      "intervention": "post-Yoga",
      "comparator": "pre-Yoga",
      "outcome_type": "continuous",
      "intervention_events": null,
      "intervention_group_size": 19,
      "comparator_events": null,
      "comparator_group_size": 19,
      "intervention_mean": null,
      "intervention_standard_deviation": null,
      "comparator_mean": null,
      "comparator_standard_deviation": null,
      "notes": "Article states yoga practices are useful in reducing symptoms such as heaviness, fullness and pain, but only pain intensity is quantified. Pain before: median 6 (range 3\u20138, Q1=5, Q3=7, QD=1); after: median 1 (range 0\u20133, Q1=0, Q3=2, QD=1). Wilcoxon signed-rank z=\u22123.864, P<0.001. No separate quantitative data for heaviness or fullness."
    },
    {
      "pmcid": null,
      "outcome": "pain in reversible inguinal hernia",
      "intervention": "post-Yoga",
      "comparator": "pre-Yoga",
      "outcome_type": "continuous",
      "intervention_events": null,
      "intervention_group_size": 19,
      "comparator_events": null,
      "comparator_group_size": 19,
      "intervention_mean": null,
      "intervention_standard_deviation": null,
      "comparator_mean": null,
      "comparator_standard_deviation": null,
      "notes": "Pain measured on 0\u201310 numeric rating scale. Before: median 6 (range 3\u20138, Q1=5, Q3=7, QD=1); After: median 1 (range 0\u20133, Q1=0, Q3=2, QD=1). Wilcoxon signed-rank z=\u22123.864, P<0.001. Means and SDs not reported."
    },
    {
      "pmcid": null,
      "outcome": "aggravating factors in reversible inguinal hernia",
      "intervention": "post-Yoga",
      "comparator": "pre-Yoga",
      "outcome_type": "continuous",
      "intervention_events": null,
      "intervention_group_size": 19,
      "comparator_events": null,
      "comparator_group_size": 19,
      "intervention_mean": null,
      "intervention_standard_deviation": null,
      "comparator_mean": null,
      "comparator_standard_deviation": null,
      "notes": "Aggravating factors scored as count of present activities (0\u20135) among exercise/walking, bowel movement, bladder activity, lifting, coughing/sneezing. Before: median 4 (range 3\u20135, QD=0.5); After: median 1 (range 0\u20132, QD=0). Wilcoxon signed-rank z=\u22123.875, P<0.001."
    }
  ],
  "usage": {
    "input": 0,
    "output": 0
  },
  "model": "gpt",
  "strategy": "zero-shot",
  "temperature": 0.0
}