{
  "pmcid": "5498715",
  "raw_text": "```json\n[\n  {\n    \"pmcid\": null,\n    \"outcome\": \"Scores of external regulation\",\n    \"intervention\": \"Motivational interviewing through self-determination theory sessions\",\n    \"comparator\": \"Standard education session\",\n    \"outcome_type\": \"continuous\",\n    \"intervention_events\": null,\n    \"intervention_group_size\": 30,\n    \"comparator_events\": null,\n    \"comparator_group_size\": 30,\n    \"intervention_mean\": 0.43,\n    \"intervention_standard_deviation\": 1.04,\n    \"comparator_mean\": 1.19,\n    \"comparator_standard_deviation\": 1.37,\n    \"notes\": \"Follow-up at 4 months after intervention; values from Table 3 (Behavioral Regulation in Exercise Questionnaire - external regulation subscale).\",\n    \"pmcid\": null\n  },\n  {\n    \"pmcid\": null,\n    \"outcome\": \"Scores of amotivation\",\n    \"intervention\": \"Motivational interviewing through self-determination theory sessions\",\n    \"comparator\": \"Standard education session\",\n    \"outcome_type\": \"continuous\",\n    \"intervention_events\": null,\n    \"intervention_group_size\": 30,\n    \"comparator_events\": null,\n    \"comparator_group_size\": 30,\n    \"intervention_mean\": 0.06,\n    \"intervention_standard_deviation\": 0.36,\n    \"comparator_mean\": 0.58,\n    \"comparator_standard_deviation\": 0.92,\n    \"notes\": \"Follow-up at 4 months after intervention; values from Table 3 (BREQ-2 amotivation subscale).\",\n    \"pmcid\": null\n  },\n  {\n    \"pmcid\": null,\n    \"outcome\": \"Body mass index\",\n    \"intervention\": \"Motivational interviewing through self-determination theory sessions\",\n    \"comparator\": \"Standard education session\",\n    \"outcome_type\": \"continuous\",\n    \"intervention_events\": null,\n    \"intervention_group_size\": 30,\n    \"comparator_events\": null,\n    \"comparator_group_size\": 30,\n    \"intervention_mean\": 25.32,\n    \"intervention_standard_deviation\": 3.05,\n    \"comparator_mean\": 26.59,\n    \"comparator_standard_deviation\": 3.53,\n    \"notes\": \"Follow-up at 4 months after intervention; values from Table 4 (BMI, kg/m^2).\",\n    \"pmcid\": null\n  },\n  {\n    \"pmcid\": null,\n    \"outcome\": \"Sedentary behavior\",\n    \"intervention\": \"Motivational interviewing through self-determination theory sessions\",\n    \"comparator\": \"Standard education session\",\n    \"outcome_type\": \"continuous\",\n    \"intervention_events\": null,\n    \"intervention_group_size\": 30,\n    \"comparator_events\": null,\n    \"comparator_group_size\": 30,\n    \"intervention_mean\": 4.26,\n    \"intervention_standard_deviation\": 1.76,\n    \"comparator_mean\": 5.91,\n    \"comparator_standard_deviation\": 2.21,\n    \"notes\": \"Sedentary behavior in hours/day at 4\u2011month follow-up; values from Table 3.\",\n    \"pmcid\": null\n  },\n  {\n    \"pmcid\": null,\n    \"outcome\": \"agility test\",\n    \"intervention\": \"Motivational interviewing through self-determination theory sessions\",\n    \"comparator\": \"Standard education session\",\n    \"outcome_type\": \"continuous\",\n    \"intervention_events\": null,\n    \"intervention_group_size\": 30,\n    \"comparator_events\": null,\n    \"comparator_group_size\": 30,\n    \"intervention_mean\": 13.21,\n    \"intervention_standard_deviation\": 1.44,\n    \"comparator_mean\": 13.80,\n    \"comparator_standard_deviation\": 1.14,\n    \"notes\": \"9\u00d74 m agility test, time in seconds; follow-up at 4 months after intervention; values from Table 4.\",\n    \"pmcid\": null\n  },\n  {\n    \"pmcid\": null,\n    \"outcome\": \"Physical activity\",\n    \"intervention\": \"Motivational interviewing through self-determination theory sessions\",\n    \"comparator\": \"Standard education session\",\n    \"outcome_type\": \"continuous\",\n    \"intervention_events\": null,\n    \"intervention_group_size\": 30,\n    \"comparator_events\": null,\n    \"comparator_group_size\": 30,\n    \"intervention_mean\": 854.0,\n    \"intervention_standard_deviation\": 271.60,\n    \"comparator_mean\": 470.0,\n    \"comparator_standard_deviation\": 80.46,\n    \"notes\": \"Total physical activity in MET\u2011min/week at 4\u2011month follow-up; values from Table 3 (GPAQ).\",\n    \"pmcid\": null\n  },\n  {\n    \"pmcid\": null,\n    \"outcome\": \"physical fitness - flexibility\",\n    \"intervention\": \"Motivational interviewing through self-determination theory sessions\",\n    \"comparator\": \"Standard education session\",\n    \"outcome_type\": \"continuous\",\n    \"intervention_events\": null,\n    \"intervention_group_size\": 30,\n    \"comparator_events\": null,\n    \"comparator_group_size\": 30,\n    \"intervention_mean\": 35.53,\n    \"intervention_standard_deviation\": 5.87,\n    \"comparator_mean\": 26.83,\n    \"comparator_standard_deviation\": 5.47,\n    \"notes\": \"Sit-and-reach flexibility test (cm); follow-up at 4 months after intervention; values from Table 4.\",\n    \"pmcid\": null\n  },\n  {\n    \"pmcid\": null,\n    \"outcome\": \"physical fitness - muscular endurance\",\n    \"intervention\": \"Motivational interviewing through self-determination theory sessions\",\n    \"comparator\": \"Standard education session\",\n    \"outcome_type\": \"continuous\",\n    \"intervention_events\": null,\n    \"intervention_group_size\": 30,\n    \"comparator_events\": null,\n    \"comparator_group_size\": 30,\n    \"intervention_mean\": 17.83,\n    \"intervention_standard_deviation\": 2.70,\n    \"comparator_mean\": 12.48,\n    \"comparator_standard_deviation\": 2.90,\n    \"notes\": \"Sit\u2011up test, number of repetitions in 30 seconds; follow-up at 4 months after intervention; values from Table 4.\",\n    \"pmcid\": null\n  },\n  {\n    \"pmcid\": null,\n    \"outcome\": \"physical fitness - agility\",\n    \"intervention\": \"Motivational interviewing through self-determination theory sessions\",\n    \"comparator\": \"Standard education session\",\n    \"outcome_type\": \"continuous\",\n    \"intervention_events\": null,\n    \"intervention_group_size\": 30,\n    \"comparator_events\": null,\n    \"comparator_group_size\": 30,\n    \"intervention_mean\": 13.21,\n    \"intervention_standard_deviation\": 1.44,\n    \"comparator_mean\": 13.80,\n    \"comparator_standard_deviation\": 1.14,\n    \"notes\": \"Same 9\u00d74 m agility test as 'agility test' outcome; follow-up at 4 months after intervention; values from Table 4.\",\n    \"pmcid\": null\n  },\n  {\n    \"pmcid\": null,\n    \"outcome\": \"physical fitness - cardiorespiratory endurance\",\n    \"intervention\": \"Motivational interviewing through self-determination theory sessions\",\n    \"comparator\": \"Standard education session\",\n    \"outcome_type\": \"continuous\",\n    \"intervention_events\": null,\n    \"intervention_group_size\": 30,\n    \"comparator_events\": null,\n    \"comparator_group_size\": 30,\n    \"intervention_mean\": 39.10,\n    \"intervention_standard_deviation\": 2.76,\n    \"comparator_mean\": 37.99,\n    \"comparator_standard_deviation\": 2.14,\n    \"notes\": \"Maximal oxygen uptake (VO2max, units as reported by Quinn step test formula); follow-up at 4 months after intervention; values from Table 4.\",\n    \"pmcid\": null\n  },\n  {\n    \"pmcid\": null,\n    \"outcome\": \"Scores of intrinsic motivation\",\n    \"intervention\": \"Motivational interviewing through self-determination theory sessions\",\n    \"comparator\": \"Standard education session\",\n    \"outcome_type\": \"continuous\",\n    \"intervention_events\": null,\n    \"intervention_group_size\": 30,\n    \"comparator_events\": null,\n    \"comparator_group_size\": 30,\n    \"intervention_mean\": 13.50,\n    \"intervention_standard_deviation\": 1.79,\n    \"comparator_mean\": 5.51,\n    \"comparator_standard_deviation\": 2.39,\n    \"notes\": \"Intrinsic motivation subscale of BREQ\u20112 at 4\u2011month follow-up; values from Table 3.\",\n    \"pmcid\": null\n  },\n  {\n    \"pmcid\": null,\n    \"outcome\": \"Scores of perception of competence\",\n    \"intervention\": \"Motivational interviewing through self-determination theory sessions\",\n    \"comparator\": \"Standard education session\",\n    \"outcome_type\": \"continuous\",\n    \"intervention_events\": null,\n    \"intervention_group_size\": 30,\n    \"comparator_events\": null,\n    \"comparator_group_size\": 30,\n    \"intervention_mean\": 17.20,\n    \"intervention_standard_deviation\": 3.46,\n    \"comparator_mean\": 14.10,\n    \"comparator_standard_deviation\": 3.82,\n    \"notes\": \"Perception of competence subscale of Psychological Need Satisfaction in Exercise Scale at 4\u2011month follow-up; values from Table 3.\",\n    \"pmcid\": null\n  },\n  {\n    \"pmcid\": null,\n    \"outcome\": \"Scores of perception of autonomy\",\n    \"intervention\": \"Motivational interviewing through self-determination theory sessions\",\n    \"comparator\": \"Standard education session\",\n    \"outcome_type\": \"continuous\",\n    \"intervention_events\": null,\n    \"intervention_group_size\": 30,\n    \"comparator_events\": null,\n    \"comparator_group_size\": 30,\n    \"intervention_mean\": 30.40,\n    \"intervention_standard_deviation\": 2.83,\n    \"comparator_mean\": 19.85,\n    \"comparator_standard_deviation\": 5.24,\n    \"notes\": \"Perception of autonomy subscale of Psychological Need Satisfaction in Exercise Scale at 4\u2011month follow-up; values from Table 3.\",\n    \"pmcid\": null\n  },\n  {\n    \"pmcid\": null,\n    \"outcome\": \"Scores of enjoyment\",\n    \"intervention\": \"Motivational interviewing through self-determination theory sessions\",\n    \"comparator\": \"Standard education session\",\n    \"outcome_type\": \"continuous\",\n    \"intervention_events\": null,\n    \"intervention_group_size\": 30,\n    \"comparator_events\": null,\n    \"comparator_group_size\": 30,\n    \"intervention_mean\": 30.0,\n    \"intervention_standard_deviation\": 3.83,\n    \"comparator_mean\": 24.89,\n    \"comparator_standard_deviation\": 5.20,\n    \"notes\": \"Enjoyment motive subscale of MPAM\u2011R at 4\u2011month follow-up; values from Table 3.\",\n    \"pmcid\": null\n  },\n  {\n    \"pmcid\": null,\n    \"outcome\": \"Scores of health care climate\",\n    \"intervention\": \"Motivational interviewing through self-determination theory sessions\",\n    \"comparator\": \"Standard education session\",\n    \"outcome_type\": \"continuous\",\n    \"intervention_events\": null,\n    \"intervention_group_size\": 30,\n    \"comparator_events\": null,\n    \"comparator_group_size\": 30,\n    \"intervention_mean\": 83.10,\n    \"intervention_standard_deviation\": 1.37,\n    \"comparator_mean\": 69.57,\n    \"comparator_standard_deviation\": 1.61,\n    \"notes\": \"Health Care Climate Questionnaire total score at 4\u2011month follow-up; values from Table 3.\",\n    \"pmcid\": null\n  }\n]\n```",
  "extraction": [
    {
      "pmcid": null,
      "outcome": "Scores of external regulation",
      "intervention": "Motivational interviewing through self-determination theory sessions",
      "comparator": "Standard education session",
      "outcome_type": "continuous",
      "intervention_events": null,
      "intervention_group_size": 30,
      "comparator_events": null,
      "comparator_group_size": 30,
      "intervention_mean": 0.43,
      "intervention_standard_deviation": 1.04,
      "comparator_mean": 1.19,
      "comparator_standard_deviation": 1.37,
      "notes": "Follow-up at 4 months after intervention; values from Table 3 (Behavioral Regulation in Exercise Questionnaire - external regulation subscale)."
    },
    {
      "pmcid": null,
      "outcome": "Scores of amotivation",
      "intervention": "Motivational interviewing through self-determination theory sessions",
      "comparator": "Standard education session",
      "outcome_type": "continuous",
      "intervention_events": null,
      "intervention_group_size": 30,
      "comparator_events": null,
      "comparator_group_size": 30,
      "intervention_mean": 0.06,
      "intervention_standard_deviation": 0.36,
      "comparator_mean": 0.58,
      "comparator_standard_deviation": 0.92,
      "notes": "Follow-up at 4 months after intervention; values from Table 3 (BREQ-2 amotivation subscale)."
    },
    {
      "pmcid": null,
      "outcome": "Body mass index",
      "intervention": "Motivational interviewing through self-determination theory sessions",
      "comparator": "Standard education session",
      "outcome_type": "continuous",
      "intervention_events": null,
      "intervention_group_size": 30,
      "comparator_events": null,
      "comparator_group_size": 30,
      "intervention_mean": 25.32,
      "intervention_standard_deviation": 3.05,
      "comparator_mean": 26.59,
      "comparator_standard_deviation": 3.53,
      "notes": "Follow-up at 4 months after intervention; values from Table 4 (BMI, kg/m^2)."
    },
    {
      "pmcid": null,
      "outcome": "Sedentary behavior",
      "intervention": "Motivational interviewing through self-determination theory sessions",
      "comparator": "Standard education session",
      "outcome_type": "continuous",
      "intervention_events": null,
      "intervention_group_size": 30,
      "comparator_events": null,
      "comparator_group_size": 30,
      "intervention_mean": 4.26,
      "intervention_standard_deviation": 1.76,
      "comparator_mean": 5.91,
      "comparator_standard_deviation": 2.21,
      "notes": "Sedentary behavior in hours/day at 4\u2011month follow-up; values from Table 3."
    },
    {
      "pmcid": null,
      "outcome": "agility test",
      "intervention": "Motivational interviewing through self-determination theory sessions",
      "comparator": "Standard education session",
      "outcome_type": "continuous",
      "intervention_events": null,
      "intervention_group_size": 30,
      "comparator_events": null,
      "comparator_group_size": 30,
      "intervention_mean": 13.21,
      "intervention_standard_deviation": 1.44,
      "comparator_mean": 13.8,
      "comparator_standard_deviation": 1.14,
      "notes": "9\u00d74 m agility test, time in seconds; follow-up at 4 months after intervention; values from Table 4."
    },
    {
      "pmcid": null,
      "outcome": "Physical activity",
      "intervention": "Motivational interviewing through self-determination theory sessions",
      "comparator": "Standard education session",
      "outcome_type": "continuous",
      "intervention_events": null,
      "intervention_group_size": 30,
      "comparator_events": null,
      "comparator_group_size": 30,
      "intervention_mean": 854.0,
      "intervention_standard_deviation": 271.6,
      "comparator_mean": 470.0,
      "comparator_standard_deviation": 80.46,
      "notes": "Total physical activity in MET\u2011min/week at 4\u2011month follow-up; values from Table 3 (GPAQ)."
    },
    {
      "pmcid": null,
      "outcome": "physical fitness - flexibility",
      "intervention": "Motivational interviewing through self-determination theory sessions",
      "comparator": "Standard education session",
      "outcome_type": "continuous",
      "intervention_events": null,
      "intervention_group_size": 30,
      "comparator_events": null,
      "comparator_group_size": 30,
      "intervention_mean": 35.53,
      "intervention_standard_deviation": 5.87,
      "comparator_mean": 26.83,
      "comparator_standard_deviation": 5.47,
      "notes": "Sit-and-reach flexibility test (cm); follow-up at 4 months after intervention; values from Table 4."
    },
    {
      "pmcid": null,
      "outcome": "physical fitness - muscular endurance",
      "intervention": "Motivational interviewing through self-determination theory sessions",
      "comparator": "Standard education session",
      "outcome_type": "continuous",
      "intervention_events": null,
      "intervention_group_size": 30,
      "comparator_events": null,
      "comparator_group_size": 30,
      "intervention_mean": 17.83,
      "intervention_standard_deviation": 2.7,
      "comparator_mean": 12.48,
      "comparator_standard_deviation": 2.9,
      "notes": "Sit\u2011up test, number of repetitions in 30 seconds; follow-up at 4 months after intervention; values from Table 4."
    },
    {
      "pmcid": null,
      "outcome": "physical fitness - agility",
      "intervention": "Motivational interviewing through self-determination theory sessions",
      "comparator": "Standard education session",
      "outcome_type": "continuous",
      "intervention_events": null,
      "intervention_group_size": 30,
      "comparator_events": null,
      "comparator_group_size": 30,
      "intervention_mean": 13.21,
      "intervention_standard_deviation": 1.44,
      "comparator_mean": 13.8,
      "comparator_standard_deviation": 1.14,
      "notes": "Same 9\u00d74 m agility test as 'agility test' outcome; follow-up at 4 months after intervention; values from Table 4."
    },
    {
      "pmcid": null,
      "outcome": "physical fitness - cardiorespiratory endurance",
      "intervention": "Motivational interviewing through self-determination theory sessions",
      "comparator": "Standard education session",
      "outcome_type": "continuous",
      "intervention_events": null,
      "intervention_group_size": 30,
      "comparator_events": null,
      "comparator_group_size": 30,
      "intervention_mean": 39.1,
      "intervention_standard_deviation": 2.76,
      "comparator_mean": 37.99,
      "comparator_standard_deviation": 2.14,
      "notes": "Maximal oxygen uptake (VO2max, units as reported by Quinn step test formula); follow-up at 4 months after intervention; values from Table 4."
    },
    {
      "pmcid": null,
      "outcome": "Scores of intrinsic motivation",
      "intervention": "Motivational interviewing through self-determination theory sessions",
      "comparator": "Standard education session",
      "outcome_type": "continuous",
      "intervention_events": null,
      "intervention_group_size": 30,
      "comparator_events": null,
      "comparator_group_size": 30,
      "intervention_mean": 13.5,
      "intervention_standard_deviation": 1.79,
      "comparator_mean": 5.51,
      "comparator_standard_deviation": 2.39,
      "notes": "Intrinsic motivation subscale of BREQ\u20112 at 4\u2011month follow-up; values from Table 3."
    },
    {
      "pmcid": null,
      "outcome": "Scores of perception of competence",
      "intervention": "Motivational interviewing through self-determination theory sessions",
      "comparator": "Standard education session",
      "outcome_type": "continuous",
      "intervention_events": null,
      "intervention_group_size": 30,
      "comparator_events": null,
      "comparator_group_size": 30,
      "intervention_mean": 17.2,
      "intervention_standard_deviation": 3.46,
      "comparator_mean": 14.1,
      "comparator_standard_deviation": 3.82,
      "notes": "Perception of competence subscale of Psychological Need Satisfaction in Exercise Scale at 4\u2011month follow-up; values from Table 3."
    },
    {
      "pmcid": null,
      "outcome": "Scores of perception of autonomy",
      "intervention": "Motivational interviewing through self-determination theory sessions",
      "comparator": "Standard education session",
      "outcome_type": "continuous",
      "intervention_events": null,
      "intervention_group_size": 30,
      "comparator_events": null,
      "comparator_group_size": 30,
      "intervention_mean": 30.4,
      "intervention_standard_deviation": 2.83,
      "comparator_mean": 19.85,
      "comparator_standard_deviation": 5.24,
      "notes": "Perception of autonomy subscale of Psychological Need Satisfaction in Exercise Scale at 4\u2011month follow-up; values from Table 3."
    },
    {
      "pmcid": null,
      "outcome": "Scores of enjoyment",
      "intervention": "Motivational interviewing through self-determination theory sessions",
      "comparator": "Standard education session",
      "outcome_type": "continuous",
      "intervention_events": null,
      "intervention_group_size": 30,
      "comparator_events": null,
      "comparator_group_size": 30,
      "intervention_mean": 30.0,
      "intervention_standard_deviation": 3.83,
      "comparator_mean": 24.89,
      "comparator_standard_deviation": 5.2,
      "notes": "Enjoyment motive subscale of MPAM\u2011R at 4\u2011month follow-up; values from Table 3."
    },
    {
      "pmcid": null,
      "outcome": "Scores of health care climate",
      "intervention": "Motivational interviewing through self-determination theory sessions",
      "comparator": "Standard education session",
      "outcome_type": "continuous",
      "intervention_events": null,
      "intervention_group_size": 30,
      "comparator_events": null,
      "comparator_group_size": 30,
      "intervention_mean": 83.1,
      "intervention_standard_deviation": 1.37,
      "comparator_mean": 69.57,
      "comparator_standard_deviation": 1.61,
      "notes": "Health Care Climate Questionnaire total score at 4\u2011month follow-up; values from Table 3."
    }
  ],
  "usage": {
    "input": 0,
    "output": 0
  },
  "model": "gpt",
  "strategy": "zero-shot",
  "temperature": 0.0
}