{
  "pmcid": "57750",
  "raw_text": "```json\n[\n  {\n    \"pmcid\": \"null\",\n    \"outcome\": \"Death or myocardial infarction\",\n    \"intervention\": \"eptifibatide\",\n    \"comparator\": \"placebo\",\n    \"outcome_type\": \"binary\",\n    \"intervention_events\": 14.2,\n    \"intervention_group_size\": null,\n    \"comparator_events\": 15.7,\n    \"comparator_group_size\": null,\n    \"intervention_mean\": null,\n    \"intervention_standard_deviation\": null,\n    \"comparator_mean\": null,\n    \"comparator_standard_deviation\": null,\n    \"notes\": \"Values are 30-day CEC-adjudicated event rates (%) for the overall PURSUIT population, taken from Table 5: 'Overall 14.2 15.7 0.042'. Absolute counts and group sizes are not reported in this article.\",\n    \"pmcid\": null\n  },\n  {\n    \"pmcid\": \"null\",\n    \"outcome\": \"Myocardial infarction\",\n    \"intervention\": \"eptifibatide\",\n    \"comparator\": \"placebo\",\n    \"outcome_type\": \"binary\",\n    \"intervention_events\": 12.6,\n    \"intervention_group_size\": null,\n    \"comparator_events\": 13.6,\n    \"comparator_group_size\": null,\n    \"intervention_mean\": null,\n    \"intervention_standard_deviation\": null,\n    \"comparator_mean\": null,\n    \"comparator_standard_deviation\": null,\n    \"notes\": \"Values are 30-day CEC-adjudicated MI event rates (%) for the overall PURSUIT population, taken from Table 5: 'Overall 12.6 13.6 0.137'. Absolute counts and group sizes are not reported in this article.\",\n    \"pmcid\": null\n  }\n]\n```",
  "extraction": [
    {
      "pmcid": null,
      "outcome": "Death or myocardial infarction",
      "intervention": "eptifibatide",
      "comparator": "placebo",
      "outcome_type": "binary",
      "intervention_events": 14.2,
      "intervention_group_size": null,
      "comparator_events": 15.7,
      "comparator_group_size": null,
      "intervention_mean": null,
      "intervention_standard_deviation": null,
      "comparator_mean": null,
      "comparator_standard_deviation": null,
      "notes": "Values are 30-day CEC-adjudicated event rates (%) for the overall PURSUIT population, taken from Table 5: 'Overall 14.2 15.7 0.042'. Absolute counts and group sizes are not reported in this article."
    },
    {
      "pmcid": null,
      "outcome": "Myocardial infarction",
      "intervention": "eptifibatide",
      "comparator": "placebo",
      "outcome_type": "binary",
      "intervention_events": 12.6,
      "intervention_group_size": null,
      "comparator_events": 13.6,
      "comparator_group_size": null,
      "intervention_mean": null,
      "intervention_standard_deviation": null,
      "comparator_mean": null,
      "comparator_standard_deviation": null,
      "notes": "Values are 30-day CEC-adjudicated MI event rates (%) for the overall PURSUIT population, taken from Table 5: 'Overall 12.6 13.6 0.137'. Absolute counts and group sizes are not reported in this article."
    }
  ],
  "usage": {
    "input": 0,
    "output": 0
  },
  "model": "gpt",
  "strategy": "zero-shot",
  "temperature": 0.0
}